agent.py
autonomous_agent.py
bash_loops.py
client.py
error_handler.py
loop_detector.py
lsp_plugins.py
output_formatter.py
preflight.py
progress.py
ralph_detector.py
retry_manager.py
security.py
setup_mcp.py
skills_manager.py
version.py
claude_harness-4.0.3.dist-info/licenses/LICENSE
harness_data/__init__.py
harness_data/.claude/skills/code-quality/SKILL.md
harness_data/.claude/skills/harness-patterns/SKILL.md
harness_data/.claude/skills/linear-workflow/SKILL.md
harness_data/.claude/skills/lsp-navigation/SKILL.md
harness_data/.claude/skills/project-patterns/SKILL.md
harness_data/.claude/skills/puppeteer-testing/SKILL.md
infra/__init__.py
infra/healer.py
prompts/__init__.py
prompts/app_spec.txt
prompts/bugfix_mode_prompt.md
prompts/coding_prompt.md
prompts/enhancement_coding_prompt.md
prompts/enhancement_initializer_prompt.md
prompts/generic_e2e_requirements.md
prompts/generic_regression_requirements.md
prompts/infrastructure_validation_gate.md
prompts/initializer_prompt.md
prompts/project_structure.md
prompts/quality_gates.md
prompts/smoke_test_gate.md
prompts/test_execution_gate.md
prompts/test_quality_standards.md
prompts/validation_mode_prompt.md
validators/__init__.py
validators/browser_cleanup_hook.py
validators/completion_promise_validator.py
validators/e2e_hook.py
validators/e2e_verifier.py
validators/secrets_hook.py
validators/secrets_scanner.py
validators/test_runner.py
claude_harness-4.0.3.dist-info/METADATA
claude_harness-4.0.3.dist-info/WHEEL
claude_harness-4.0.3.dist-info/entry_points.txt
claude_harness-4.0.3.dist-info/top_level.txt
claude_harness-4.0.3.dist-info/RECORD
