Metadata-Version: 2.4
Name: claude-harness
Version: 4.0.3
Summary: Production-ready autonomous coding harness using Claude Code SDK
Home-page: https://github.com/nirmalarya/claude-harness
Author: Nirmalarya
Author-email: Nirmalarya <hello@nirmalarya.com>
License-Expression: MIT
Project-URL: Homepage, https://github.com/nirmalarya/claude-harness
Project-URL: Documentation, https://github.com/nirmalarya/claude-harness/blob/main/README.md
Project-URL: Repository, https://github.com/nirmalarya/claude-harness
Project-URL: Issues, https://github.com/nirmalarya/claude-harness/issues
Keywords: claude,autonomous,coding,agent,ai,sdk
Classifier: Development Status :: 4 - Beta
Classifier: Intended Audience :: Developers
Classifier: Programming Language :: Python :: 3
Classifier: Programming Language :: Python :: 3.10
Classifier: Programming Language :: Python :: 3.11
Classifier: Programming Language :: Python :: 3.12
Classifier: Programming Language :: Python :: 3.13
Requires-Python: >=3.10
License-File: LICENSE
Requires-Dist: claude-code-sdk>=0.0.25
Requires-Dist: pyyaml>=6.0
Dynamic: author
Dynamic: home-page
Dynamic: license-file
Dynamic: requires-python
